tribe/__init__.py
tribe/config.py
tribe/emails.py
tribe/extract.py
tribe/progress.py
tribe/stats.py
tribe/utils.py
tribe/version.py
tribe/viz.py
tribe-1.3.data/scripts/tribe-admin.py
tribe-1.3.dist-info/DESCRIPTION.rst
tribe-1.3.dist-info/METADATA
tribe-1.3.dist-info/RECORD
tribe-1.3.dist-info/WHEEL
tribe-1.3.dist-info/metadata.json
tribe-1.3.dist-info/top_level.txt
