Metadata-Version: 2.0
Name: tribe
Version: 1.3
Summary: An graph extraction tool for email MBox files
Home-page: https://github.com/DistrictDataLabs/tribe
Author: Benjamin Bengfort
Author-email: bbengfort@districtdatalabs.com
License: MIT
Download-URL: https://github.com/DistrictDataLabs/tribe/tarball/v1.3
Keywords: graph,networkx,data science,analysis,social network
Platform: UNKNOWN
Classifier: Development Status :: 5 - Production/Stable
Classifier: Environment :: Console
Classifier: Intended Audience :: Science/Research
Classifier: License :: OSI Approved :: MIT License
Classifier: Natural Language :: English
Classifier: Operating System :: OS Independent
Classifier: Programming Language :: Python
Classifier: Programming Language :: Python :: 2.7
Classifier: Programming Language :: Python :: 3.5
Classifier: Topic :: Communications :: Email
Classifier: Topic :: Scientific/Engineering :: Information Analysis
Classifier: Topic :: Scientific/Engineering :: Visualization
Classifier: Topic :: Utilities
Requires-Dist: confire (==0.2.0)
Requires-Dist: future (==0.15.2)
Requires-Dist: matplotlib (==1.5.1)
Requires-Dist: networkx (==1.11)
Requires-Dist: python-dateutil (==2.5.3)
Requires-Dist: python-louvain (==0.5)
Requires-Dist: six (==1.10.0)
